sylegendarium/__init__.py
sylegendarium/legendarium.py
sylegendarium-0.0.2.dist-info/METADATA
sylegendarium-0.0.2.dist-info/WHEEL
sylegendarium-0.0.2.dist-info/licenses/LICENSE
sylegendarium-0.0.2.dist-info/RECORD
