Metadata-Version: 2.4
Name: sylegendarium
Version: 0.0.2
Summary: Legendarium is a simple package to store metrics and parameters of an experiment
Project-URL: Homepage, https://bender.us.es/syanes/legendarium
Project-URL: Issues, https://bender.us.es/syanes/legendarium/issues
Author-email: Samuel Yanes Luis <syanes@us.es>
License-Expression: MIT
License-File: LICENSE
Classifier: Development Status :: 3 - Alpha
Classifier: Intended Audience :: Education
Classifier: Operating System :: MacOS :: MacOS X
Classifier: Operating System :: Microsoft :: Windows
Classifier: Programming Language :: Python :: 2
Classifier: Programming Language :: Python :: 3
